LianaiHouheixue/README.md
LianaiHouheixue/__init__.py
LianaiHouheixue/__main__.py
LianaiHouheixue/file.epub
LianaiHouheixue/index.html
LianaiHouheixue/css/__init__.py
LianaiHouheixue/css/annotations.css
LianaiHouheixue/css/main.css
LianaiHouheixue/css/normalize.css
LianaiHouheixue/css/popup.css
LianaiHouheixue/font/__init__.py
LianaiHouheixue/font/fontello.eot
LianaiHouheixue/font/fontello.svg
LianaiHouheixue/font/fontello.ttf
LianaiHouheixue/font/fontello.woff
LianaiHouheixue/img/__init__.py
LianaiHouheixue/img/annotator-glyph-sprite.png
LianaiHouheixue/img/annotator-icon-sprite.png
LianaiHouheixue/img/apple-touch-icon.png
LianaiHouheixue/img/cancelfullscreen.png
LianaiHouheixue/img/close.png
LianaiHouheixue/img/fullscreen.png
LianaiHouheixue/img/loader.gif
LianaiHouheixue/img/menu-icon.png
LianaiHouheixue/img/save.png
LianaiHouheixue/img/saved.png
LianaiHouheixue/img/settings-s.png
LianaiHouheixue/img/settings.png
LianaiHouheixue/img/star.png
LianaiHouheixue/js/__init__.py
LianaiHouheixue/js/epub.js
LianaiHouheixue/js/epub.min.js
LianaiHouheixue/js/epub.min.map
LianaiHouheixue/js/hooks.min.js
LianaiHouheixue/js/hooks.min.map
LianaiHouheixue/js/reader.js
LianaiHouheixue/js/reader.js.map
LianaiHouheixue/js/reader.min.js
LianaiHouheixue/js/reader.min.map
LianaiHouheixue/js/hooks/__init__.py
LianaiHouheixue/js/hooks/extensions/__init__.py
LianaiHouheixue/js/hooks/extensions/highlight.js
LianaiHouheixue/js/libs/__init__.py
LianaiHouheixue/js/libs/jquery.min.js
LianaiHouheixue/js/libs/localforage.min.js
LianaiHouheixue/js/libs/screenfull.js
LianaiHouheixue/js/libs/screenfull.min.js
LianaiHouheixue/js/libs/zip.min.js
LianaiHouheixue/js/plugins/__init__.py
LianaiHouheixue/js/plugins/hypothesis.js
LianaiHouheixue/js/plugins/search.js
lianai_houheixue-2022.10.11.0.dist-info/METADATA
lianai_houheixue-2022.10.11.0.dist-info/WHEEL
lianai_houheixue-2022.10.11.0.dist-info/entry_points.txt
lianai_houheixue-2022.10.11.0.dist-info/top_level.txt
lianai_houheixue-2022.10.11.0.dist-info/RECORD
